errorHelp/__init__.py
errorHelp/errorHelp.py
error_help-0.0.3.dist-info/LICENSE
error_help-0.0.3.dist-info/METADATA
error_help-0.0.3.dist-info/WHEEL
error_help-0.0.3.dist-info/top_level.txt
error_help-0.0.3.dist-info/RECORD
