Metadata-Version: 2.1
Name: error-help
Version: 0.0.3
Summary: A small package to automate searching your errors.
Home-page: https://github.com/topcatthomas/errorHelp
Author: Thomas C
Author-email: topcat.thomas.phone@outlook.com
License: UNKNOWN
Platform: UNKNOWN
Classifier: Programming Language :: Python :: 3
Classifier: License :: OSI Approved :: MIT License
Classifier: Operating System :: OS Independent
Requires-Python: >=3.6
